sallron/__init__.py
sallron/enforcer.py
sallron/eye.py
sallron/db/__init__.py
sallron/db/caching.py
sallron/db/mongo.py
sallron/extensions/__init__.py
sallron/extensions/e_raptor.py
sallron/util/__init__.py
sallron/util/discord.py
sallron/util/executor.py
sallron/util/logger.py
sallron/util/parser.py
sallron/util/s3.py
sallron/util/settings.py
sallron/util/stats.py
sallron/util/modifiers/__init__.py
sallron/util/modifiers/get_vtex_categories_mod.py
sallron-0.2.15.dist-info/LICENSE
sallron-0.2.15.dist-info/METADATA
sallron-0.2.15.dist-info/WHEEL
sallron-0.2.15.dist-info/top_level.txt
sallron-0.2.15.dist-info/RECORD
