Metadata-Version: 2.1
Name: sallron
Version: 0.2.15
Summary: Collected data middleware for DB.
Home-page: https://github.com/elint-tech/sallron/
Author: elint-tech
Author-email: contato@elint.com.br
License: proprietary
Download-URL: https://github.com/elint-tech/e-raptor/dist/sallron-0.2.15tar.gz
Keywords: sallron,sauron,data-middleware,data-aggregator,pymongo,schedule,walrus
Platform: UNKNOWN
Classifier: Development Status :: 4 - Beta
Classifier: Intended Audience :: Developers
Classifier: Intended Audience :: Information Technology
Classifier: Intended Audience :: System Administrators
Classifier: Intended Audience :: Other Audience
Classifier: Topic :: Software Development
Classifier: Topic :: Internet
Classifier: Topic :: Internet :: WWW/HTTP :: HTTP Servers
Classifier: Topic :: Utilities
Classifier: License :: Other/Proprietary License
Classifier: Programming Language :: Python :: 3
Classifier: Programming Language :: Python :: 3.4
Classifier: Programming Language :: Python :: 3.5
Classifier: Programming Language :: Python :: 3.6
Classifier: Programming Language :: Python :: 3.7
Classifier: Operating System :: OS Independent
Requires-Dist: discord-logger (==1.1.2)
Requires-Dist: pymongo[srv] (==3.11.0)
Requires-Dist: requests (==2.31.0)
Requires-Dist: schedule (==0.6.0)
Requires-Dist: walrus (==0.8.1)
Requires-Dist: psutil (==5.7.3)
Requires-Dist: boto3
Requires-Dist: pytz (==2020.1)
Requires-Dist: dill (==0.3.3)
